armada_api_client/__init__.py
armada_api_client/api/__init__.py
armada_api_client/api/alarm_elements/__init__.py
armada_api_client/api/alarm_elements/alarm_elements_count_filter_with_get.py
armada_api_client/api/alarm_elements/alarm_elements_count_filter_with_post.py
armada_api_client/api/alarm_elements/alarm_elements_distinct_equ_path_group_sub_group_name_get.py
armada_api_client/api/alarm_elements/alarm_elements_distinct_equ_path_group_sub_group_name_post.py
armada_api_client/api/alarm_elements/alarm_elements_distinct_equ_type_group_sub_group_name_get.py
armada_api_client/api/alarm_elements/alarm_elements_distinct_equ_type_group_sub_group_name_post.py
armada_api_client/api/alarm_elements/alarm_elements_filter_with_get.py
armada_api_client/api/alarm_elements/alarm_elements_filter_with_post.py
armada_api_client/api/alarm_elements/alarm_elements_get_by_id.py
armada_api_client/api/ameo/__init__.py
armada_api_client/api/ameo/ameo_get_assets.py
armada_api_client/api/api_keys/__init__.py
armada_api_client/api/api_keys/api_keys_count_filter_with_get.py
armada_api_client/api/api_keys/api_keys_count_filter_with_post.py
armada_api_client/api/api_keys/api_keys_create.py
armada_api_client/api/api_keys/api_keys_create_bulk.py
armada_api_client/api/api_keys/api_keys_delete_bulk.py
armada_api_client/api/api_keys/api_keys_delete_by_id.py
armada_api_client/api/api_keys/api_keys_filter_with_get.py
armada_api_client/api/api_keys/api_keys_filter_with_post.py
armada_api_client/api/api_keys/api_keys_get_by_id.py
armada_api_client/api/api_keys/api_keys_modify.py
armada_api_client/api/api_keys/api_keys_modify_bulk.py
armada_api_client/api/authentication/__init__.py
armada_api_client/api/authentication/authentication_log_out_api.py
armada_api_client/api/authentication/authentication_log_out_root.py
armada_api_client/api/authentication/authentication_login.py
armada_api_client/api/categories/__init__.py
armada_api_client/api/categories/categories_get.py
armada_api_client-1.dist-info/METADATA
armada_api_client-1.dist-info/WHEEL
armada_api_client-1.dist-info/RECORD
